LICENSE.txt
setup.cfg
setup.py
pyexception_notifier/__init__.py
pyexception_notifier/config.py
pyexception_notifier/main_.py
pyexception_notifier/test_notifier.py
pyexception_notifier.egg-info/PKG-INFO
pyexception_notifier.egg-info/SOURCES.txt
pyexception_notifier.egg-info/dependency_links.txt
pyexception_notifier.egg-info/requires.txt
pyexception_notifier.egg-info/top_level.txt
pyexception_notifier/exceptions/__init__.py
pyexception_notifier/exceptions/exceptions.py
pyexception_notifier/notify_sources_clients/__init__.py
pyexception_notifier/notify_sources_clients/telegram/__init__.py
pyexception_notifier/notify_sources_clients/telegram/client.py
pyexception_notifier/utils/__init__.py
pyexception_notifier/utils/enums.py
pyexception_notifier/utils/exception_parsers.py