Metadata-Version: 2.1
Name: pyexception-notifier
Version: 0.0.4
Summary: Exception notifier
Home-page: UNKNOWN
Author: r.islyamgali
License: MIT
Platform: UNKNOWN
Requires-Python: >=3.8
License-File: LICENSE.txt
